alphai/__init__.py
alphai/alphai.py
alphai_api-0.0.6.dist-info/METADATA
alphai_api-0.0.6.dist-info/WHEEL
alphai_api-0.0.6.dist-info/top_level.txt
alphai_api-0.0.6.dist-info/RECORD
