Metadata-Version: 2.1
Name: alphai-api
Version: 0.0.6
Summary: AlphAI API
Home-page: https://learningrobots.ai
Author: Learning Robots
Author-email: contact@learningrobots.ai
License: UNKNOWN
Platform: UNKNOWN
Classifier: Programming Language :: Python :: 3
Classifier: License :: OSI Approved :: MIT License
Classifier: Operating System :: OS Independent
Requires-Python: >=3.7
Requires-Dist: pynput
Requires-Dist: numpy
